gqlcli/__init__.py
gqlcli/federation.py
gqlcli/generator.py
gqlcli/main.py
gqlcli/make_schema.py
gqlcli/playground.py
gqlcli/schema_visitor.py
gqlcli/utils.py
gqlcli-0.4.0.dist-info/entry_points.txt
gqlcli-0.4.0.dist-info/LICENSE
gqlcli-0.4.0.dist-info/WHEEL
gqlcli-0.4.0.dist-info/METADATA
gqlcli-0.4.0.dist-info/RECORD
