Metadata-Version: 2.1
Name: gqlcli
Version: 0.4.0
Summary: Auto-generate GraphQL Type, Resolver and Query.
Home-page: https://github.com/syfun
Author: syfun
Author-email: sunyu418@gmail.com
Requires-Python: >=3.8
Classifier: Programming Language :: Python :: 3
Classifier: Programming Language :: Python :: 3.8
Classifier: Programming Language :: Python :: 3.9
Requires-Dist: click (>=7,<8)
Requires-Dist: graphql-core (>=3)
Requires-Dist: requests (>=2.25.1,<3.0.0)
Requires-Dist: waitress (>=2.0.0,<3.0.0)
